input_module/__init__.py
input_module/test.py
input_module/text_input.py
einput-0.1.dist-info/LICENSE
einput-0.1.dist-info/METADATA
einput-0.1.dist-info/WHEEL
einput-0.1.dist-info/top_level.txt
einput-0.1.dist-info/RECORD
