Metadata-Version: 2.1
Name: einput
Version: 0.1
Summary: A input manager
Home-page: https://github.com/LuciferMonao
Author: Lucifer Monao
Author-email: lucifermonao@gmx.com
License: UNKNOWN
Platform: UNKNOWN
Classifier: Programming Language :: Python :: 3
Classifier: License :: OSI Approved :: MIT License
Classifier: Operating System :: OS Independent
Requires-Python: >=3.7
